g2pc/__init__.py
g2pc/cedict.pkl
g2pc/crf100.bin
g2pc/g2pc.py
g2pC-0.9.9.3.dist-info/LICENSE
g2pC-0.9.9.3.dist-info/METADATA
g2pC-0.9.9.3.dist-info/WHEEL
g2pC-0.9.9.3.dist-info/top_level.txt
g2pC-0.9.9.3.dist-info/RECORD
